elias_fano
