Metadata-Version: 2.1
Name: elias-fano
Version: 1.0.2
Summary: Python package implementing an educational version of Elias-Fano succint structure. This package is not thought for efficient data storing as the superior and inferior data vectors are implemented as strings to show the results step by step for educational purposes.
Home-page: https://github.com/LucaCappelletti94/elias_fano
Author: Luca Cappelletti
Author-email: cappelletti.luca94@gmail.com
License: MIT
Platform: UNKNOWN
Classifier: Development Status :: 3 - Alpha
Classifier: License :: OSI Approved :: MIT License
Classifier: Programming Language :: Python :: 3
Provides-Extra: test
